multinmrfit/__init__.py
multinmrfit/__main__.py
multinmrfit/base/__init__.py
multinmrfit/base/io.py
multinmrfit/base/process.py
multinmrfit/base/spectrum.py
multinmrfit/models/__init__.py
multinmrfit/models/base_model.py
multinmrfit/models/model_doublet.py
multinmrfit/models/model_doublet_of_doublet.py
multinmrfit/models/model_quartet.py
multinmrfit/models/model_singlet.py
multinmrfit/models/model_triplet.py
multinmrfit/ui/01_Inputs_&_Outputs.py
multinmrfit/ui/__init__.py
multinmrfit/ui/pages/02_Process_spectra.py
multinmrfit/ui/pages/03_Process_from_reference.py
multinmrfit/ui/pages/04_Results_visualisation.py
multinmrfit-2.1.3.dist-info/LICENSE
multinmrfit-2.1.3.dist-info/METADATA
multinmrfit-2.1.3.dist-info/WHEEL
multinmrfit-2.1.3.dist-info/entry_points.txt
multinmrfit-2.1.3.dist-info/top_level.txt
multinmrfit-2.1.3.dist-info/RECORD
