Metadata-Version: 2.1
Name: multinmrfit
Version: 2.1.3
Summary: Fitting 1D NMR spectra
Home-page: https://github.com/NMRTeamTBI/MultiNMRFit
Author: Pierre Millard, Cyril Charlier
Author-email: charlier@insa-toulouse.fr
Project-URL: Bug Tracker, https://github.com/NMRTeamTBI/MultiNMRFit/issues
Classifier: Programming Language :: Python :: 3
Classifier: License :: OSI Approved :: GNU General Public License (GPL)
Classifier: Operating System :: OS Independent
Requires-Python: >=3.8
License-File: LICENSE
Requires-Dist: pandas>=1.3.4
Requires-Dist: numpy>=1.21.4
Requires-Dist: scipy>=1.12.0
Requires-Dist: nmrglue>=0.6
Requires-Dist: plotly>=5.18.0
Requires-Dist: streamlit>=1.3.1
Requires-Dist: sess-i>=0.0.2
Requires-Dist: streamlit-multipage>=0.0.18
